yohsin3d/__init__.py
yohsin3d/communicators/__init__.py
yohsin3d/communicators/y3d_communicator/__init__.py
yohsin3d/communicators/y3d_communicator/bit_codec.py
yohsin3d/communicators/y3d_communicator/communicator.py
yohsin3d/core/__init__.py
yohsin3d/core/agent.py
yohsin3d/core/behavior.py
yohsin3d/core/spawner.py
yohsin3d/core/body/__init__.py
yohsin3d/core/body/body_model.py
yohsin3d/core/body/enums.py
yohsin3d/core/body/nao_joint.py
yohsin3d/core/common/__init__.py
yohsin3d/core/common/agent_location.py
yohsin3d/core/common/constants.py
yohsin3d/core/common/ground_truth_model.py
yohsin3d/core/common/joints.py
yohsin3d/core/communicator/__init__.py
yohsin3d/core/communicator/base_communicator.py
yohsin3d/core/localizer/__init__.py
yohsin3d/core/localizer/base_localizer.py
yohsin3d/core/network/__init__.py
yohsin3d/core/network/constants.py
yohsin3d/core/network/parser.py
yohsin3d/core/network/server.py
yohsin3d/core/world/__init__.py
yohsin3d/core/world/enums.py
yohsin3d/core/world/world_model.py
yohsin3d/drawing/__init__.py
yohsin3d/drawing/rv_draw.py
yohsin3d/localizers/__init__.py
yohsin3d/localizers/geometric_localizer.py
yohsin3d/localizers/ground_truth_localizer.py
yohsin3d/locomotors/__init__.py
yohsin3d/locomotors/getup/__init__.py
yohsin3d/locomotors/getup/fall_recovery.py
yohsin3d/locomotors/pfs/__init__.py
yohsin3d/locomotors/pfs/pfs_turn.py
yohsin3d/locomotors/pfs/pfs_walk.py
yohsin3d/locomotors/pfs/utility.py
yohsin3d/movement/__init__.py
yohsin3d/movement/movement.py
yohsin3d/movement/y3d_movements.py
yohsin3d-0.4.5.dist-info/LICENSE
yohsin3d-0.4.5.dist-info/METADATA
yohsin3d-0.4.5.dist-info/WHEEL
yohsin3d-0.4.5.dist-info/top_level.txt
yohsin3d-0.4.5.dist-info/RECORD
