Metadata-Version: 2.1
Name: yohsin3d
Version: 0.4.5
Summary: Program your own RoboCup 3D soccer playing agents in python
Home-page: https://github.com/FC-Yohsin/yohsin3d
Author: Habib Shahzad, Abuzar Rasool, Faaz Abidi
Author-email: habibshehzad55@gmail.com, availabuzar@gmail.com, hasanfaaz10@gmail.com
License: MIT
Keywords: robocup,soccer,3d,simulation,agents,robotics,machine learning,python,artificial intelligence,locomotion,localization
Classifier: Development Status :: 3 - Alpha
Classifier: Intended Audience :: Developers
Classifier: Intended Audience :: Education
Classifier: Intended Audience :: Science/Research
Classifier: License :: OSI Approved :: MIT License
Classifier: Operating System :: OS Independent
Classifier: Programming Language :: Python
Classifier: Programming Language :: Python :: 3
Classifier: Programming Language :: Python :: 3.6
Classifier: Programming Language :: Python :: 3.7
Classifier: Programming Language :: Python :: 3.8
Classifier: Programming Language :: Python :: 3.9
Classifier: Topic :: Scientific/Engineering
Classifier: Topic :: Scientific/Engineering :: Artificial Intelligence
Classifier: Topic :: Software Development
Classifier: Topic :: Software Development :: Libraries
Classifier: Topic :: Software Development :: Libraries :: Python Modules
Requires-Python: >=3.6
License-File: LICENSE
